ciflypy-0.1.3.dist-info/METADATA
ciflypy-0.1.3.dist-info/WHEEL
ciflypy/__init__.py
ciflypy/__init__.pyi
ciflypy/ciflypy.pypy311-pp73-x86-linux-gnu.so
ciflypy/py.typed
ciflypy-0.1.3.dist-info/RECORD
